{"pageContext":{"tag":"react-hooks","posts":[{"slug":"load-everything-lazily-with-intersectionobserver","draft":false,"title":"Load everything lazily with IntersectionObserver","createdAt":"2019-01-23T09:34:52.446Z","updatedAt":"2019-01-23T09:34:52.446Z","preface":"<p>I believe it is clear for every web developer that we should care about size and amount of resources we load to a client (browser). Let&#39;s have a look at a simple technique we can use to improve initial load of web pages.</p>","tags":["react-hooks","reactjs","web-api"],"timeToRead":3}]}}